sltkpy/__init__.py
sltkpy/tokenizer.py
sltkpy/models/vocab.json
sltkpy-1.0.0.data/data/shared/vocab.json
sltkpy-1.0.0.dist-info/licenses/LICENSE
sltkpy-1.0.0.dist-info/METADATA
sltkpy-1.0.0.dist-info/WHEEL
sltkpy-1.0.0.dist-info/top_level.txt
sltkpy-1.0.0.dist-info/RECORD
